bojdata/__init__.py
bojdata/_version.py
bojdata/api.py
bojdata/batch.py
bojdata/bulk_downloader.py
bojdata/cli.py
bojdata/comprehensive_search.py
bojdata/core.py
bojdata/exceptions.py
bojdata/fred_mapping.py
bojdata/metadata.py
bojdata/releases.py
bojdata/retry.py
bojdata/search.py
bojdata/test_mode.py
bojdata/transformations.py
bojdata/utils.py
bojdata/data/boj_data_mapping.json
bojdata-0.0.2.dist-info/licenses/LICENSE
bojdata-0.0.2.dist-info/METADATA
bojdata-0.0.2.dist-info/WHEEL
bojdata-0.0.2.dist-info/entry_points.txt
bojdata-0.0.2.dist-info/top_level.txt
bojdata-0.0.2.dist-info/RECORD
